FLApy/DataManagement.py
FLApy/LAHanalysis.py
FLApy/LAcalculator.py
FLApy/Visualization.py
FLApy/__init__.py
FLApy-2.1.2.dist-info/LICENSE
FLApy-2.1.2.dist-info/METADATA
FLApy-2.1.2.dist-info/WHEEL
FLApy-2.1.2.dist-info/top_level.txt
FLApy-2.1.2.dist-info/RECORD
