Metadata-Version: 2.1
Name: FLApy
Version: 2.1.2
Summary: Forest Light availability heterogeneity Analysis in Python
Home-page: https://github.com/niB-gnaW/FLApy2023
Author: Bin Wang
Author-email: wb931022@hotmail.com
Classifier: Programming Language :: Python :: 3.11
Classifier: License :: OSI Approved :: MIT License
Classifier: Operating System :: OS Independent
Requires-Python: >=3.11
License-File: LICENSE
Requires-Dist: numpy ==1.26.4
Requires-Dist: scipy
Requires-Dist: matplotlib
Requires-Dist: open3d
Requires-Dist: pyvista
Requires-Dist: PVGeo
Requires-Dist: laspy
Requires-Dist: pandas
Requires-Dist: tqdm
Requires-Dist: miniball
Requires-Dist: xarray
Requires-Dist: joblib
Requires-Dist: scikit-learn
Requires-Dist: seaborn
Requires-Dist: vtk
